psyrun/__init__.py
psyrun/exceptions.py
psyrun/jobs.py
psyrun/main.py
psyrun/mapper.py
psyrun/pspace.py
psyrun/scheduler.py
psyrun/tasks.py
psyrun/version.py
psyrun/backend/__init__.py
psyrun/backend/base.py
psyrun/backend/distribute.py
psyrun/backend/load_balancing.py
psyrun/store/__init__.py
psyrun/store/base.py
psyrun/store/h5.py
psyrun/store/np_shape.py
psyrun/store/npz.py
psyrun/store/pickle.py
psyrun/utils/__init__.py
psyrun/utils/doc.py
psyrun/utils/example.py
psyrun/utils/testing.py
psyrun/utils/venv.py
psyrun-0.8.0.dist-info/METADATA
psyrun-0.8.0.dist-info/RECORD
psyrun-0.8.0.dist-info/WHEEL
psyrun-0.8.0.dist-info/entry_points.txt
psyrun-0.8.0.dist-info/top_level.txt
