Metadata-Version: 2.1
Name: psyrun
Version: 0.8.0
Summary: Easy parameter space evaluation and serial farming.
Home-page: https://github.com/jgosmann/psyrun
Author: Jan Gosmann
Author-email: jan@hyper-world.de
License: MIT
Platform: UNKNOWN
Classifier: Development Status :: 4 - Beta
Classifier: Environment :: Console
Classifier: Intended Audience :: Science/Research
Classifier: License :: OSI Approved :: MIT License
Classifier: Natural Language :: English
Classifier: Operating System :: Unix
Classifier: Programming Language :: Python :: 2.7
Classifier: Programming Language :: Python :: 3
Provides: psyrun
Provides-Extra: h5
Provides-Extra: npz
Provides-Extra: parallel_map
Requires-Dist: six
Provides-Extra: h5
Requires-Dist: numpy; extra == 'h5'
Requires-Dist: tables; extra == 'h5'
Provides-Extra: npz
Requires-Dist: numpy; extra == 'npz'
Provides-Extra: parallel_map
Requires-Dist: joblib; extra == 'parallel_map'
